.gitignore
.readthedocs.yaml
HISTORY.md
LICENSE.md
MANIFEST.in
README.md
conftest.py
pyproject.toml
requirements.txt
setup.py
.github/workflows/publish-to-pypi.yml
.github/workflows/test_package.yml
docs/Makefile
docs/make.bat
docs/requirements.txt
docs/source/calibration.rst
docs/source/ccf.rst
docs/source/ccf_tests.rst
docs/source/conf.py
docs/source/index.rst
docs/source/install.rst
docs/source/intro.rst
docs/source/pca_subtraction.rst
docs/source/pipeline.rst
docs/source/plot_functions.rst
docs/source/utility_functions.rst
docs/source/_static/co_map.png
pcassie/__init__.py
pcassie/calibration.py
pcassie/ccf.py
pcassie/ccf_tests.py
pcassie/pca_subtraction.py
pcassie/pipeline.py
pcassie/plot_functions.py
pcassie/utility_functions.py
pcassie.egg-info/PKG-INFO
pcassie.egg-info/SOURCES.txt
pcassie.egg-info/dependency_links.txt
pcassie.egg-info/top_level.txt