Metadata-Version: 2.1
Name: pcassie
Version: 0.1.6
Summary: A Pincipal Component Pipeline based on Damiano et al. 2019
Author: Kenny T. Phan
Author-email: kenny.phan@yale.edu
Classifier: License :: OSI Approved :: MIT License
Classifier: Intended Audience :: Science/Research
Classifier: Programming Language :: Python :: 3.13
Classifier: Topic :: Scientific/Engineering :: Astronomy
Classifier: Topic :: Scientific/Engineering :: Physics
License-File: LICENSE.md
